YAPI_heureka_code/Lexer.py
YAPI_heureka_code/__init__.py
YAPI_heureka_code/token_data.py
YAPI_heureka_code/token_gruppen.py
YAPI_heureka_code/token_tools.py
YAPI_heureka_code/yapi.py
YAPI_heureka_code-1.1.2.dist-info/LICENSE.txt
YAPI_heureka_code-1.1.2.dist-info/METADATA
YAPI_heureka_code-1.1.2.dist-info/WHEEL
YAPI_heureka_code-1.1.2.dist-info/top_level.txt
YAPI_heureka_code-1.1.2.dist-info/RECORD
