Metadata-Version: 2.1
Name: YAPI-heureka-code
Version: 1.1.2
Summary: Moeglichkeit eine kleine API mit Lexer zu erstellen
Home-page: https://github.com/heureka-code/YAPI-heureka-code
Author: heureka-code
License: MIT
Download-URL: https://github.com/heureka-code/YAPI-heureka-code/archive/refs/tags/1.1.1.tar.gz
Platform: UNKNOWN
